setup.py
bin/jia
jia/__init__.py
jia/cli.py
jia/textcolor.py
jia.egg-info/PKG-INFO
jia.egg-info/SOURCES.txt
jia.egg-info/dependency_links.txt
jia.egg-info/requires.txt
jia.egg-info/top_level.txt